bigpy/__init__.py
bigpy3-0.0.2.dev2.dist-info/METADATA
bigpy3-0.0.2.dev2.dist-info/RECORD
bigpy3-0.0.2.dev2.dist-info/WHEEL
bigpy3-0.0.2.dev2.dist-info/top_level.txt
